<features name="oozie-plugin" version="4.0.0-RC6">
  <feature name="oozie-plugin" version="4.0.0-RC6">
    <bundle> mvn:io.subutai/oozie-plugin-api/4.0.0-RC6</bundle>
    <bundle> mvn:io.subutai/oozie-plugin-impl/4.0.0-RC6</bundle>>
    <bundle> mvn:io.subutai/oozie-plugin-cli/4.0.0-RC6</bundle>
    <bundle> mvn:io.subutai/oozie-plugin-rest/4.0.0-RC6</bundle>
  </feature>
    <feature name="oozie-plugin-war" version="4.0.0-RC6">
        <bundle> war:mvn:io.subutai/oozie-plugin-webui/4.0.0-RC6/war?Webapp-Context=oozie-plugin-war</bundle>
    </feature>
</features>