<features name="shark-plugin" version="4.0.9">
  <feature name="shark-plugin" version="4.0.9">
    <bundle>mvn:io.subutai.plugin/shark-plugin-api/4.0.9</bundle>
    <bundle>mvn:io.subutai.plugin/shark-plugin-impl/4.0.9</bundle>
    <bundle>mvn:io.subutai.plugin/shark-plugin-cli/4.0.9</bundle>
    <bundle>mvn:io.subutai.plugin/shark-plugin-rest/4.0.9</bundle>
  </feature>
    <feature name="shark-plugin-war" version="4.0.9">
        <bundle> war:mvn:io.subutai.plugin/shark-plugin-webui/4.0.9/war?Webapp-Context=shark-plugin-war</bundle>
    </feature>
</features>