<features name="presto-plugin" version="5.0.1">
  <feature name="presto-plugin" version="5.0.1">
    <bundle>mvn:io.subutai.plugin/presto-plugin-api/5.0.1</bundle>
    <bundle>mvn:io.subutai.plugin/presto-plugin-impl/5.0.1</bundle>
    <bundle>mvn:io.subutai.plugin/presto-plugin-cli/5.0.1</bundle>
    <bundle>mvn:io.subutai.plugin/presto-plugin-rest/5.0.1</bundle>
  </feature>
    <feature name="presto-plugin-war" version="5.0.1">
        <bundle> war:mvn:io.subutai.plugin/presto-plugin-webui/5.0.1/war?Webapp-Context=presto-plugin-war</bundle>
    </feature>
</features>